LICENSE
MANIFEST.in
README.rst
setup.py
sixfeetup/__init__.py
sixfeetup.recipe.runvars.egg-info/PKG-INFO
sixfeetup.recipe.runvars.egg-info/SOURCES.txt
sixfeetup.recipe.runvars.egg-info/dependency_links.txt
sixfeetup.recipe.runvars.egg-info/entry_points.txt
sixfeetup.recipe.runvars.egg-info/requires.txt
sixfeetup.recipe.runvars.egg-info/top_level.txt
sixfeetup.recipe.runvars.egg-info/zip-safe
sixfeetup/recipe/__init__.py
sixfeetup/recipe/runvars/__init__.py