Metadata-Version: 1.1
Name: sixfeetup.recipe.runvars
Version: 0.2.0
Summary: Buildout recipe to define variables from external commands.
Home-page: https://github.com/sixfeetup/sixfeetup.recipe.runvars
Author: Glenn Franxman
Author-email: glenn@sixfeetup.com
License: BSD
Keywords: runvars recipe
Platform: UNKNOWN
Classifier: Framework :: Buildout
Classifier: Framework :: Buildout :: Recipe
Classifier: Programming Language :: Python
Classifier: Programming Language :: Python :: 2
Classifier: Programming Language :: Python :: 2.7
Classifier: Programming Language :: Python :: 3
Classifier: Programming Language :: Python :: 3.6
Classifier: Development Status :: 5 - Production/Stable
Classifier: Topic :: Software Development :: Libraries :: Python Modules
Classifier: License :: OSI Approved :: BSD License
